reqtracker/__init__.py
reqtracker/__main__.py
reqtracker/cli.py
reqtracker/config.py
reqtracker/dynamic_tracker.py
reqtracker/generator.py
reqtracker/mappings.py
reqtracker/static_analyzer.py
reqtracker/tracker.py
reqtracker/utils.py
reqtracker-1.0.7.dist-info/licenses/LICENSE
reqtracker-1.0.7.dist-info/METADATA
reqtracker-1.0.7.dist-info/WHEEL
reqtracker-1.0.7.dist-info/entry_points.txt
reqtracker-1.0.7.dist-info/top_level.txt
reqtracker-1.0.7.dist-info/RECORD
