Metadata-Version: 2.4
Name: reqtracker
Version: 1.0.7
Summary: Intelligent Python dependency tracking and requirements.txt generation
Author-email: Oleksii Shcherbak <oleksii_shcherbak@icloud.com>
License: MIT
Project-URL: Homepage, https://github.com/oleksii-shcherbak/reqtracker
Project-URL: Repository, https://github.com/oleksii-shcherbak/reqtracker
Project-URL: Issues, https://github.com/oleksii-shcherbak/reqtracker/issues
Project-URL: Documentation, https://github.com/oleksii-shcherbak/reqtracker#readme
Project-URL: Changelog, https://github.com/oleksii-shcherbak/reqtracker/releases
Keywords: dependencies,requirements,tracking,automation,development,pip,packaging,dependency-management,static-analysis,ast
Classifier: Development Status :: 4 - Beta
Classifier: Intended Audience :: Developers
Classifier: License :: OSI Approved :: MIT License
Classifier: Programming Language :: Python :: 3
Classifier: Programming Language :: Python :: 3.8
Classifier: Programming Language :: Python :: 3.9
Classifier: Programming Language :: Python :: 3.10
Classifier: Programming Language :: Python :: 3.11
Classifier: Programming Language :: Python :: 3.12
Classifier: Programming Language :: Python :: 3.13
Classifier: Topic :: Software Development :: Libraries :: Python Modules
Classifier: Topic :: Software Development :: Build Tools
Classifier: Topic :: System :: Systems Administration
Classifier: Topic :: Utilities
Classifier: Environment :: Console
Classifier: Operating System :: OS Independent
Classifier: Typing :: Typed
Requires-Python: >=3.8
License-File: LICENSE
Requires-Dist: tomli>=2.0.0; python_version < "3.11"
Provides-Extra: dev
Requires-Dist: pytest>=7.0; extra == "dev"
Requires-Dist: pytest-cov>=4.0; extra == "dev"
Requires-Dist: black>=23.0; extra == "dev"
Requires-Dist: isort>=5.0; extra == "dev"
Requires-Dist: flake8>=6.0; extra == "dev"
Requires-Dist: mypy>=1.0; extra == "dev"
Requires-Dist: pre-commit>=3.0; extra == "dev"
Dynamic: license-file
